<?xml version="1.0" encoding="UTF-8" standalone="no"?>
<!-- Generated Apr 19, 2024, 5:09:41 PM by Hibernate Tools 5.6.15.Final --><!DOCTYPE hibernate-mapping PUBLIC "-//Hibernate/Hibernate Mapping DTD 3.0//EN" "http://www.hibernate.org/dtd/hibernate-mapping-3.0.dtd">
<hibernate-mapping>
    <class catalog="sys" name="com.shoestoredb.entity2.UserSummaryByStatementLatency" optimistic-lock="none" table="user_summary_by_statement_latency">
        <comment>VIEW</comment>
        <composite-id class="com.shoestoredb.entity2.UserSummaryByStatementLatencyId" name="id">
            <key-property name="user" type="string">
                <column length="32" name="user"/>
            </key-property>
            <key-property name="total" type="big_integer">
                <column name="total" precision="42" scale="0"/>
            </key-property>
            <key-property name="totalLatency" type="string">
                <column length="11" name="total_latency"/>
            </key-property>
            <key-property name="maxLatency" type="string">
                <column length="11" name="max_latency"/>
            </key-property>
            <key-property name="lockLatency" type="string">
                <column length="11" name="lock_latency"/>
            </key-property>
            <key-property name="cpuLatency" type="string">
                <column length="11" name="cpu_latency"/>
            </key-property>
            <key-property name="rowsSent" type="big_integer">
                <column name="rows_sent" precision="42" scale="0"/>
            </key-property>
            <key-property name="rowsExamined" type="big_integer">
                <column name="rows_examined" precision="42" scale="0"/>
            </key-property>
            <key-property name="rowsAffected" type="big_integer">
                <column name="rows_affected" precision="42" scale="0"/>
            </key-property>
            <key-property name="fullScans" type="big_integer">
                <column name="full_scans" precision="43" scale="0"/>
            </key-property>
        </composite-id>
    </class>
</hibernate-mapping>
